README.md
requirements.txt
setup.cfg
setup.py
examples/__init__.py
examples/asset_provided_since_example.py
examples/basic_info_example.py
examples/get_balance_example.py
examples/get_dominance_example.py
examples/get_sentiment_example.py
examples/provided_date_formats.py
pycortecs/__init__.py
pycortecs/cortecs_api.py
pycortecs.egg-info/PKG-INFO
pycortecs.egg-info/SOURCES.txt
pycortecs.egg-info/dependency_links.txt
pycortecs.egg-info/requires.txt
pycortecs.egg-info/top_level.txt
pycortecs/services/__init__.py
pycortecs/services/base_services.py
pycortecs/services/media_services.py
pycortecs/utility/__init__.py
pycortecs/utility/enumerations.py
pycortecs/utility/utils.py
pycortecs/utility/exceptions/__init__.py
pycortecs/utility/exceptions/not_connected_error.py
pycortecs/utility/exceptions/not_specified_error.py
pycortecs/utility/exceptions/paramter_error.py