Metadata-Version: 2.1
Name: pycortecs
Version: 0.1.5
Summary: Python client to access crypto sentiment
Home-page: https://github.com/cortecs-ai/pycortecs
Author: Cortecs
Author-email: alexander.steiner@cortecs.ai
License: MIT
Download-URL: https://github.com/cortecs-ai/pycortecs/archive/refs/tags/0.1.5.zip
Keywords: trading,pandas,finance,crypto,bitcoin,sentiment
Platform: UNKNOWN
Requires-Python: >=3.6
